odoo/addons/l10n_it_website_sale_fiscalcode/README.rst
odoo/addons/l10n_it_website_sale_fiscalcode/__init__.py
odoo/addons/l10n_it_website_sale_fiscalcode/__manifest__.py
odoo/addons/l10n_it_website_sale_fiscalcode/controllers/__init__.py
odoo/addons/l10n_it_website_sale_fiscalcode/controllers/main.py
odoo/addons/l10n_it_website_sale_fiscalcode/i18n/de.po
odoo/addons/l10n_it_website_sale_fiscalcode/i18n/es.po
odoo/addons/l10n_it_website_sale_fiscalcode/i18n/it.po
odoo/addons/l10n_it_website_sale_fiscalcode/i18n/l10n_it_website_sale_fiscalcode.pot
odoo/addons/l10n_it_website_sale_fiscalcode/i18n/sl.po
odoo/addons/l10n_it_website_sale_fiscalcode/readme/CONTRIBUTORS.md
odoo/addons/l10n_it_website_sale_fiscalcode/readme/DESCRIPTION.md
odoo/addons/l10n_it_website_sale_fiscalcode/readme/USAGE.md
odoo/addons/l10n_it_website_sale_fiscalcode/static/description/icon.png
odoo/addons/l10n_it_website_sale_fiscalcode/static/description/index.html
odoo/addons/l10n_it_website_sale_fiscalcode/views/templates.xml
odoo_addon_l10n_it_website_sale_fiscalcode-16.0.1.0.0.2.dist-info/METADATA
odoo_addon_l10n_it_website_sale_fiscalcode-16.0.1.0.0.2.dist-info/WHEEL
odoo_addon_l10n_it_website_sale_fiscalcode-16.0.1.0.0.2.dist-info/top_level.txt
odoo_addon_l10n_it_website_sale_fiscalcode-16.0.1.0.0.2.dist-info/RECORD
