Metadata-Version: 2.1
Name: odoo-addon-l10n_it_website_sale_fiscalcode
Version: 16.0.1.0.0.2
Requires-Python: >=3.10
Requires-Dist: odoo-addon-l10n_it_fiscalcode>=16.0dev,<16.1dev
Requires-Dist: odoo>=16.0a,<16.1dev
Summary: Website Sale FiscalCode
Home-page: https://github.com/OCA/l10n-italy/tree/14.0/l10n_it_website_sale_fiscalcode
License: AGPL-3
Author: Agile Business Group,Odoo Community Association (OCA)
Author-email: support@odoo-community.org
Classifier: Programming Language :: Python
Classifier: Framework :: Odoo
Classifier: Framework :: Odoo :: 16.0
Classifier: License :: OSI Approved :: GNU Affero General Public License v3
